github_traffic.py
github_traffic-0.2.0.dist-info/entry_points.txt
github_traffic-0.2.0.dist-info/LICENSE
github_traffic-0.2.0.dist-info/WHEEL
github_traffic-0.2.0.dist-info/METADATA
github_traffic-0.2.0.dist-info/RECORD
