Metadata-Version: 2.1
Name: github-traffic
Version: 0.2.0
Summary: Summarize Github traffic stats across repositories.
Home-page: https://github.com/jashandeep-sohi/github-traffic
License: GPLv3
Author: Jashandeep Sohi
Author-email: jashandeep.s.sohi@gmail.com
Requires-Python: >=3.8,<4.0
Classifier: License :: Other/Proprietary License
Classifier: Programming Language :: Python :: 3
Classifier: Programming Language :: Python :: 3.8
Classifier: Programming Language :: Python :: 3.9
Requires-Dist: PyGithub (>=1.43.8)
Requires-Dist: click (>=7)
Requires-Dist: click-aliases (>=1.0.1,<2.0.0)
Requires-Dist: terminaltables (>=3.1.0,<4.0.0)
Project-URL: Repository, https://github.com/jashandeep-sohi/github-traffic
